LICENSE
MANIFEST.in
README.rst
ez_setup.py
setup.py
cassandra/__init__.py
cassandra/auth.py
cassandra/buffer.pxd
cassandra/bytesio.pxd
cassandra/bytesio.pyx
cassandra/cluster.py
cassandra/cmurmur3.c
cassandra/compat.py
cassandra/concurrent.py
cassandra/connection.py
cassandra/cqltypes.py
cassandra/cython_deps.py
cassandra/cython_marshal.pyx
cassandra/cython_utils.pxd
cassandra/cython_utils.pyx
cassandra/deserializers.pxd
cassandra/deserializers.pyx
cassandra/encoder.py
cassandra/ioutils.pyx
cassandra/marshal.py
cassandra/metadata.py
cassandra/metrics.py
cassandra/murmur3.py
cassandra/numpyFlags.h
cassandra/numpy_parser.pyx
cassandra/obj_parser.pyx
cassandra/parsing.pxd
cassandra/parsing.pyx
cassandra/policies.py
cassandra/pool.py
cassandra/protocol.py
cassandra/query.py
cassandra/row_parser.pyx
cassandra/segment.py
cassandra/timestamps.py
cassandra/tuple.pxd
cassandra/type_codes.pxd
cassandra/type_codes.py
cassandra/util.py
cassandra/column_encryption/_policies.py
cassandra/column_encryption/policies.py
cassandra/cqlengine/__init__.py
cassandra/cqlengine/columns.py
cassandra/cqlengine/connection.py
cassandra/cqlengine/functions.py
cassandra/cqlengine/management.py
cassandra/cqlengine/models.py
cassandra/cqlengine/named.py
cassandra/cqlengine/operators.py
cassandra/cqlengine/query.py
cassandra/cqlengine/statements.py
cassandra/cqlengine/usertype.py
cassandra/datastax/__init__.py
cassandra/datastax/cloud/__init__.py
cassandra/datastax/graph/__init__.py
cassandra/datastax/graph/graphson.py
cassandra/datastax/graph/query.py
cassandra/datastax/graph/types.py
cassandra/datastax/graph/fluent/__init__.py
cassandra/datastax/graph/fluent/_predicates.py
cassandra/datastax/graph/fluent/_query.py
cassandra/datastax/graph/fluent/_serializers.py
cassandra/datastax/graph/fluent/predicates.py
cassandra/datastax/graph/fluent/query.py
cassandra/datastax/graph/fluent/serializers.py
cassandra/datastax/insights/__init__.py
cassandra/datastax/insights/registry.py
cassandra_driver_fork.egg-info/PKG-INFO
cassandra_driver_fork.egg-info/SOURCES.txt
cassandra_driver_fork.egg-info/dependency_links.txt
cassandra_driver_fork.egg-info/requires.txt
cassandra_driver_fork.egg-info/top_level.txt