Metadata-Version: 2.1
Name: cassandra-driver-fork
Version: 3.28.2
Summary:  DataStax Driver for Apache Cassandra
Home-page: http://github.com/datastax/python-driver
Author: DataStax
License: UNKNOWN
Project-URL: Documentation, https://docs.datastax.com/en/developer/python-driver/latest/
Project-URL: Source, https://github.com/datastax/python-driver/
Project-URL: Issues, https://datastax-oss.atlassian.net/browse/PYTHON
Keywords: cassandra,cql,orm,dse,graph
Platform: UNKNOWN
Classifier: Development Status :: 5 - Production/Stable
Classifier: Intended Audience :: Developers
Classifier: License :: OSI Approved :: Apache Software License
Classifier: Natural Language :: English
Classifier: Operating System :: OS Independent
Classifier: Programming Language :: Python
Classifier: Programming Language :: Python :: 3.7
Classifier: Programming Language :: Python :: 3.8
Classifier: Programming Language :: Python :: Implementation :: CPython
Classifier: Programming Language :: Python :: Implementation :: PyPy
Classifier: Topic :: Software Development :: Libraries :: Python Modules
Provides-Extra: cle
Provides-Extra: graph
License-File: LICENSE
